easyTui/__init__.py
easyTui-0.5.dist-info/LICENSE
easyTui-0.5.dist-info/METADATA
easyTui-0.5.dist-info/WHEEL
easyTui-0.5.dist-info/top_level.txt
easyTui-0.5.dist-info/RECORD
