Metadata-Version: 2.1
Name: easyTui
Version: 0.5
Summary: Very simple TUI module for python
Home-page: https://github.com/Ninnjah/easyTui
Author: Ninnjah
Author-email: yand.man4@gmail.com
License: UNKNOWN
Platform: UNKNOWN
Classifier: Programming Language :: Python :: 3
Classifier: License :: OSI Approved :: MIT License
Classifier: Operating System :: OS Independent
Requires-Python: >=3.6
